pybdp/__init__.py
pybdp/block.py
pybdp/convenience.py
pybdp/processor.py
pybdp/project.py
pybdp/schema.py
pybdp/space.py
pybdp/system.py
pybdp/toolbox.py
pybdp/ui.py
pybdp/wire.py
pybdp/workbench.py
pybdp/schemas/bdp.schema.json
pybdp/schemas/block.schema.json
pybdp/schemas/processor.schema.json
pybdp/schemas/space.schema.json
pybdp/schemas/system.schema.json
pybdp/schemas/toolbox.schema.json
pybdp/schemas/wire.schema.json
pybdp/schemas/workbench.schema.json
pybdp-0.2.3.dist-info/METADATA
pybdp-0.2.3.dist-info/WHEEL
pybdp-0.2.3.dist-info/top_level.txt
pybdp-0.2.3.dist-info/RECORD
