Metadata-Version: 2.4
Name: pybdp
Version: 0.2.3
Summary: A library for creating block diagrams based on the block diagram protocol.
Author-email: Sean McOwen <Sean@Block.Science>
Classifier: Programming Language :: Python :: 3
Classifier: License :: OSI Approved :: MIT License
Classifier: Operating System :: OS Independent
Requires-Python: >=3.7
Requires-Dist: jsonschema>=4.21.1
Requires-Dist: jsonref
Requires-Dist: IPython
